plonegovbr/__init__.py
plonegovbr/socialmedia/__init__.py
plonegovbr/socialmedia/configure.zcml
plonegovbr/socialmedia/dependencies.zcml
plonegovbr/socialmedia/interfaces.py
plonegovbr/socialmedia/permissions.zcml
plonegovbr/socialmedia/profiles.zcml
plonegovbr/socialmedia/testing.py
plonegovbr/socialmedia/utils.py
plonegovbr/socialmedia/behaviors/__init__.py
plonegovbr/socialmedia/behaviors/base.py
plonegovbr/socialmedia/behaviors/configure.zcml
plonegovbr/socialmedia/behaviors/social_links.py
plonegovbr/socialmedia/behaviors/social_media.py
plonegovbr/socialmedia/locales/__init__.py
plonegovbr/socialmedia/locales/__main__.py
plonegovbr/socialmedia/locales/plonegovbr.socialmedia.pot
plonegovbr/socialmedia/locales/de/LC_MESSAGES/plonegovbr.socialmedia.po
plonegovbr/socialmedia/locales/en/LC_MESSAGES/plonegovbr.socialmedia.mo
plonegovbr/socialmedia/locales/en/LC_MESSAGES/plonegovbr.socialmedia.po
plonegovbr/socialmedia/locales/es/LC_MESSAGES/plonegovbr.socialmedia.po
plonegovbr/socialmedia/locales/eu/LC_MESSAGES/plonegovbr.socialmedia.po
plonegovbr/socialmedia/locales/it/LC_MESSAGES/plonegovbr.socialmedia.po
plonegovbr/socialmedia/locales/pt_BR/LC_MESSAGES/plonegovbr.socialmedia.mo
plonegovbr/socialmedia/locales/pt_BR/LC_MESSAGES/plonegovbr.socialmedia.po
plonegovbr/socialmedia/profiles/default/browserlayer.xml
plonegovbr/socialmedia/profiles/default/controlpanel.xml
plonegovbr/socialmedia/profiles/default/metadata.xml
plonegovbr/socialmedia/profiles/default/types/.gitkeep
plonegovbr/socialmedia/profiles/default/types/Plone_Site.xml
plonegovbr/socialmedia/profiles/demo/metadata.xml
plonegovbr/socialmedia/profiles/demo/types/Document.xml
plonegovbr/socialmedia/profiles/uninstall/browserlayer.xml
plonegovbr/socialmedia/profiles/uninstall/types/Plone_Site.xml
plonegovbr/socialmedia/setuphandlers/__init__.py
plonegovbr/socialmedia/setuphandlers/demo.py
plonegovbr/socialmedia/setuphandlers/examplecontent/.gitkeep
plonegovbr_socialmedia-2.0.0.dist-info/METADATA
plonegovbr_socialmedia-2.0.0.dist-info/WHEEL
plonegovbr_socialmedia-2.0.0.dist-info/entry_points.txt
plonegovbr_socialmedia-2.0.0.dist-info/licenses/LICENSE.GPL
plonegovbr_socialmedia-2.0.0.dist-info/licenses/LICENSE.md
plonegovbr_socialmedia-2.0.0.dist-info/RECORD
