Metadata-Version: 2.4
Name: plonegovbr.socialmedia
Version: 2.0.0
Summary: Social media components for Plone and Volto
Project-URL: Homepage, https://github.com/plonegovbr/social-media
Project-URL: PyPI, https://pypi.org/project/plonegovbr.socialmedia
Project-URL: Source, https://github.com/plonegovbr/social-media
Project-URL: Tracker, https://github.com/plonegovbr/social-media/issues
Author-email: PloneGov-BR <gov@plone.org.br>
License-Expression: GPL-2.0-only
License-File: LICENSE.GPL
License-File: LICENSE.md
Keywords: CMS,Plone,Python
Classifier: Development Status :: 3 - Alpha
Classifier: Environment :: Web Environment
Classifier: Framework :: Plone
Classifier: Framework :: Plone :: 6.1
Classifier: Framework :: Plone :: Addon
Classifier: License :: OSI Approved :: GNU General Public License v2 (GPLv2)
Classifier: Operating System :: OS Independent
Classifier: Programming Language :: Python
Classifier: Programming Language :: Python :: 3.10
Classifier: Programming Language :: Python :: 3.11
Classifier: Programming Language :: Python :: 3.12
Classifier: Programming Language :: Python :: 3.13
Requires-Python: >=3.10
Requires-Dist: plone-api
Requires-Dist: plone-exportimport
Requires-Dist: plone-restapi
Requires-Dist: plone-volto
Requires-Dist: products-cmfplone
Provides-Extra: test
Requires-Dist: horse-with-no-namespace; extra == 'test'
Requires-Dist: plone-app-testing; extra == 'test'
Requires-Dist: plone-restapi[test]; extra == 'test'
Requires-Dist: pytest; extra == 'test'
Requires-Dist: pytest-cov; extra == 'test'
Requires-Dist: pytest-plone>=1.0.0a1; extra == 'test'
